LICENSE
msprobe/lib/__init.py__
msprobe/lib/adfs/__init.py__
msprobe/lib/adfs/adfs.py
msprobe/lib/adfs/ntlm.py
msprobe/lib/adfs/subs.txt
msprobe/lib/cli.py
msprobe/lib/exch/__init.py__
msprobe/lib/exch/exch.py
msprobe/lib/exch/ntlm.py
msprobe/lib/exch/paths.txt
msprobe/lib/exch/subs.txt
msprobe/lib/rdp/__init.py__
msprobe/lib/rdp/ntlm.py
msprobe/lib/rdp/rdp.py
msprobe/lib/rdp/subs.txt
msprobe/lib/skype/__init.py__
msprobe/lib/skype/ntlm.py
msprobe/lib/skype/skype.py
msprobe/lib/skype/subs.txt
msprobe/msprobe.py
msprobe-0.1.4.dist-info/entry_points.txt
msprobe-0.1.4.dist-info/LICENSE
msprobe-0.1.4.dist-info/WHEEL
msprobe-0.1.4.dist-info/METADATA
msprobe-0.1.4.dist-info/RECORD
