Metadata-Version: 2.1
Name: msprobe
Version: 0.1.4
Summary: Finding all things on-prem MS!
Home-page: https://github.com/puzzlpeaches/msprobe
License: BSD 3-Clause
Author: Nicholas A
Author-email: nicholasanastasirepair@gmail.com
Requires-Python: >=3.8,<4.0
Classifier: License :: Other/Proprietary License
Classifier: Programming Language :: Python :: 3
Classifier: Programming Language :: Python :: 3.10
Classifier: Programming Language :: Python :: 3.8
Classifier: Programming Language :: Python :: 3.9
Requires-Dist: bs4 (>=0.0.1,<0.0.2)
Requires-Dist: click (>=8.1.2,<9.0.0)
Requires-Dist: lxml (>=4.8.0,<5.0.0)
Requires-Dist: requests (>=2.27.1,<3.0.0)
Requires-Dist: rich (>=12.2.0,<13.0.0)
Project-URL: Repository, https://github.com/puzzlepeaches/msprobe
